CTkCodeBoxPlus/__init__.py
CTkCodeBoxPlus/add_line_nums.py
CTkCodeBoxPlus/constants.py
CTkCodeBoxPlus/ctk_code_box.py
CTkCodeBoxPlus/custom_exception_classes.py
CTkCodeBoxPlus/dataclasses.py
CTkCodeBoxPlus/keybinding.py
CTkCodeBoxPlus/text_menu.py
ctkcodeboxplus-1.2.dist-info/licenses/LICENSE
ctkcodeboxplus-1.2.dist-info/METADATA
ctkcodeboxplus-1.2.dist-info/WHEEL
ctkcodeboxplus-1.2.dist-info/top_level.txt
ctkcodeboxplus-1.2.dist-info/RECORD
