Metadata-Version: 2.4
Name: CTkCodeBoxPlus
Version: 1.2
Summary: A code editor widget for customtkinter with enhanced features
Author-email: xzyqox <xzyqox@gmail.com>
Maintainer-email: xzyqox <xzyqox@gmail.com>
License: MIT License
Project-URL: Homepage, https://github.com/KiTant/CTkCodeBoxPlus
Project-URL: Repository, https://github.com/KiTant/CTkCodeBoxPlus
Project-URL: Issues, https://github.com/KiTant/CTkCodeBoxPlus/issues
Project-URL: Documentation, https://github.com/KiTant/CTkCodeBoxPlus#readme
Keywords: customtkinter,codebox,code,gui,tkinter,context-menu
Classifier: Intended Audience :: Developers
Classifier: License :: OSI Approved :: MIT License
Classifier: Operating System :: OS Independent
Classifier: Programming Language :: Python :: 3
Classifier: Programming Language :: Python :: 3.8
Classifier: Programming Language :: Python :: 3.9
Classifier: Programming Language :: Python :: 3.10
Classifier: Programming Language :: Python :: 3.11
Classifier: Programming Language :: Python :: 3.12
Classifier: Programming Language :: Python :: 3.13
Classifier: Topic :: Software Development :: Libraries :: Python Modules
Classifier: Topic :: Software Development :: User Interfaces
Requires-Python: >=3.8
License-File: LICENSE
Requires-Dist: customtkinter>=5.0.0
Requires-Dist: pygments>=2.19.2
Requires-Dist: pyperclip>=1.9.0
Requires-Dist: tklinenums>=1.7.1
Provides-Extra: dev
Requires-Dist: pytest>=6.0; extra == "dev"
Requires-Dist: black; extra == "dev"
Requires-Dist: flake8; extra == "dev"
Dynamic: license-file
